sun22/__init__.py
sun22/audiocat.py
sun22/mmrx.py
sun22-0.0.1.dist-info/LICENSE
sun22-0.0.1.dist-info/METADATA
sun22-0.0.1.dist-info/WHEEL
sun22-0.0.1.dist-info/entry_points.txt
sun22-0.0.1.dist-info/top_level.txt
sun22-0.0.1.dist-info/RECORD
