Metadata-Version: 2.1
Name: sun22
Version: 0.0.1
Summary: Audio tunnel for secure chat, file transfer or reverse shell on Linux.
Home-page: https://github.com/ClarkFieseln/audiocat
Author: Clark Fieseln
Author-email: 
License: MIT
Project-URL: Source, https://github.com/ClarkFieseln/audiocat
Keywords: chat,messenger,reverse shell,file transfer,modem,audio,cryptography,encryption,security,cybersecurity,linux
Classifier: License :: OSI Approved :: MIT License
Classifier: Programming Language :: Python :: 3.6
Classifier: Programming Language :: Python :: 3.7
Classifier: Programming Language :: Python :: 3.8
Classifier: Programming Language :: Python :: 3.9
Classifier: Development Status :: 4 - Beta
Classifier: Environment :: Console
Classifier: Intended Audience :: End Users/Desktop
Classifier: Intended Audience :: Developers
Classifier: Operating System :: POSIX :: Linux
Classifier: Topic :: Security
License-File: LICENSE
